{"version": 0.6, "generator": "Overpass API 0.7.61.5 4133829e", "osm3s": {"timestamp_osm_base": "2023-10-08T10:37:00Z", "copyright": "The data included in this document is from www.openstreetmap.org. The data is made available under ODbL."}, "elements": [{"type": "node", "id": 18130217, "lat": 51.4925371, "lon": -0.1388857}, {"type": "node", "id": 96087864, "lat": 51.4944858, "lon": -0.1446849}, {"type": "node", "id": 128345838, "lat": 51.4870299, "lon": -0.1426449}, {"type": "node", "id": 128366302, "lat": 51.4873016, "lon": -0.1427293}, {"type": "node", "id": 128366303, "lat": 51.4875719, "lon": -0.1428082}, {"type": "node", "id": 271387568, "lat": 51.4922599, "lon": -0.1385193}, {"type": "node", "id": 273217512, "lat": 51.486687, "lon": -0.1374218, "tags": {"amenity": "parking", "name": "Dolphin Square"}}, {"type": "node", "id": 447110754, "lat": 51.4868942, "lon": -0.1460449}, {"type": "node", "id": 447110769, "lat": 51.4864205, "lon": -0.1457331}, {"type": "node", "id": 560460207, "lat": 51.4933629, "lon": -0.1422955, "tags": {"access": "customers", "amenity": "parking", "fee": "no", "name": "Pimlico Sainsbury's", "parking": "underground"}}, {"type": "node", "id": 568198494, "lat": 51.4900692, "lon": -0.1467042, "tags": {"amenity": "parking", "brand": "Q-Park", "brand:wikidata": "Q1127798", "brand:wikipedia": "en:Q-Park", "fee": "yes", "layer": "-1", "name": "Q Park Pimlico", "opening_hours": "24/7", "operator": "Q-Park", "operator:wikidata": "Q1127798", "parking": "underground"}}, {"type": "node", "id": 620025015, "lat": 51.4924554, "lon": -0.138734}, {"type": "node", "id": 620025016, "lat": 51.4924203, "lon": -0.1389575}, {"type": "node", "id": 620025020, "lat": 51.4920762, "lon": -0.1383447}, {"type": "node", "id": 620025021, "lat": 51.4920289, "lon": -0.1385246}, {"type": "node", "id": 620025023, "lat": 51.4920075, "lon": -0.1385537}, {"type": "node", "id": 711535596, "lat": 51.4941896, "lon": -0.1442824}, {"type": "node", "id": 711535597, "lat": 51.4938402, "lon": -0.1446764}, {"type": "node", "id": 711535598, "lat": 51.4938453, "lon": -0.1450637}, {"type": "node", "id": 711535600, "lat": 51.4939238, "lon": -0.1453821}, {"type": "node", "id": 711535602, "lat": 51.4945552, "lon": -0.1449371}, {"type": "node", "id": 711535603, "lat": 51.4943263, "lon": -0.1441741}, {"type": "node", "id": 805907475, "lat": 51.4922457, "lon": -0.1387885}, {"type": "node", "id": 866630971, "lat": 51.4893982, "lon": -0.1494114}, {"type": "node", "id": 881874783, "lat": 51.486968, "lon": -0.1428571}, {"type": "node", "id": 881874786, "lat": 51.4861807, "lon": -0.1426985}, {"type": "node", "id": 1143756039, "lat": 51.4894075, "lon": -0.1493836}, {"type": "node", "id": 1143756040, "lat": 51.4894071, "lon": -0.1491963}, {"type": "node", "id": 1143756041, "lat": 51.4894051, "lon": -0.1490019}, {"type": "node", "id": 1143756042, "lat": 51.4894055, "lon": -0.1489733}, {"type": "node", "id": 1143756044, "lat": 51.4892387, "lon": -0.1489733}, {"type": "node", "id": 1143756045, "lat": 51.4892565, "lon": -0.1489771}, {"type": "node", "id": 1143756047, "lat": 51.4892542, "lon": -0.1491874}, {"type": "node", "id": 1143756048, "lat": 51.4892536, "lon": -0.1493161, "tags": {"ref:GB:tflcid": "RWG055379", "traffic_calming": "hump"}}, {"type": "node", "id": 1231977787, "lat": 51.4924277, "lon": -0.1388201}, {"type": "node", "id": 1231977830, "lat": 51.4923119, "lon": -0.1385944}, {"type": "node", "id": 1232048602, "lat": 51.4920108, "lon": -0.1473425}, {"type": "node", "id": 1233349762, "lat": 51.4875378, "lon": -0.142796}, {"type": "node", "id": 1272466369, "lat": 51.4913048, "lon": -0.1495558}, {"type": "node", "id": 1272466370, "lat": 51.4913333, "lon": -0.1496246}, {"type": "node", "id": 1272466382, "lat": 51.4913757, "lon": -0.1497366}, {"type": "node", "id": 1272466384, "lat": 51.4914799, "lon": -0.1496252}, {"type": "node", "id": 1272466385, "lat": 51.491497, "lon": -0.1494887}, {"type": "node", "id": 1272466386, "lat": 51.4914267, "lon": -0.1493191}, {"type": "node", "id": 1272466410, "lat": 51.491274, "lon": -0.1494801}, {"type": "node", "id": 1272466411, "lat": 51.4915293, "lon": -0.1495782}, {"type": "node", "id": 1272481312, "lat": 51.4920749, "lon": -0.1474376}, {"type": "node", "id": 1272481314, "lat": 51.4921032, "lon": -0.1475061}, {"type": "node", "id": 1272481316, "lat": 51.4917386, "lon": -0.1479359}, {"type": "node", "id": 1272481384, "lat": 51.4916523, "lon": -0.1476021}, {"type": "node", "id": 1272481386, "lat": 51.4917319, "lon": -0.1479079}, {"type": "node", "id": 1272481492, "lat": 51.4922565, "lon": -0.1474108}, {"type": "node", "id": 1272481493, "lat": 51.4923057, "lon": -0.1475822}, {"type": "node", "id": 1272481494, "lat": 51.4923132, "lon": -0.1476438}, {"type": "node", "id": 1272481500, "lat": 51.4923065, "lon": -0.1477014}, {"type": "node", "id": 1272481505, "lat": 51.4922702, "lon": -0.1475273}, {"type": "node", "id": 1272481514, "lat": 51.4922982, "lon": -0.1477235}, {"type": "node", "id": 1272481517, "lat": 51.4923048, "lon": -0.1476834}, {"type": "node", "id": 1272481519, "lat": 51.492304, "lon": -0.1476499}, {"type": "node", "id": 1272481526, "lat": 51.4920253, "lon": -0.1475192}, {"type": "node", "id": 1283446753, "lat": 51.4923579, "lon": -0.1417407}, {"type": "node", "id": 1283446759, "lat": 51.49269, "lon": -0.1419727}, {"type": "node", "id": 1283446760, "lat": 51.4925577, "lon": -0.1421435}, {"type": "node", "id": 1537073358, "lat": 51.4947521, "lon": -0.1447971}, {"type": "node", "id": 1537073382, "lat": 51.4946893, "lon": -0.1445603}, {"type": "node", "id": 1782295982, "lat": 51.4898964, "lon": -0.1391217}, {"type": "node", "id": 1782295984, "lat": 51.4895892, "lon": -0.1388607}, {"type": "node", "id": 1782295986, "lat": 51.4898764, "lon": -0.1391016}, {"type": "node", "id": 1782295988, "lat": 51.4898429, "lon": -0.1389309}, {"type": "node", "id": 1782295990, "lat": 51.4896501, "lon": -0.1390144}, {"type": "node", "id": 1782295992, "lat": 51.4899949, "lon": -0.139166}, {"type": "node", "id": 1782295993, "lat": 51.4896342, "lon": -0.1388978}, {"type": "node", "id": 1782295998, "lat": 51.4896439, "lon": -0.1391752}, {"type": "node", "id": 1782296001, "lat": 51.4896683, "lon": -0.1390926}, {"type": "node", "id": 1782296002, "lat": 51.4898785, "lon": -0.138793}, {"type": "node", "id": 1782296003, "lat": 51.4897392, "lon": -0.1391098}, {"type": "node", "id": 1782296004, "lat": 51.4896117, "lon": -0.1388709}, {"type": "node", "id": 1782296006, "lat": 51.4898493, "lon": -0.1388439}, {"type": "node", "id": 1782296007, "lat": 51.4896639, "lon": -0.1391095}, {"type": "node", "id": 1782296013, "lat": 51.4898638, "lon": -0.1390431}, {"type": "node", "id": 1782296014, "lat": 51.4896522, "lon": -0.1391497}, {"type": "node", "id": 1782296016, "lat": 51.4899582, "lon": -0.1391526}, {"type": "node", "id": 1782296022, "lat": 51.4899256, "lon": -0.1391378}, {"type": "node", "id": 1782296026, "lat": 51.4898638, "lon": -0.1390614}, {"type": "node", "id": 1782296035, "lat": 51.4898527, "lon": -0.1389445}, {"type": "node", "id": 1782296039, "lat": 51.4898374, "lon": -0.1388955}, {"type": "node", "id": 1782296047, "lat": 51.4895984, "lon": -0.139263}, {"type": "node", "id": 1782296051, "lat": 51.4898378, "lon": -0.1389147}, {"type": "node", "id": 1782296054, "lat": 51.4899891, "lon": -0.1392035}, {"type": "node", "id": 1782296071, "lat": 51.4896522, "lon": -0.138974}, {"type": "node", "id": 1782296073, "lat": 51.4898602, "lon": -0.1388184}, {"type": "node", "id": 1782296075, "lat": 51.4896568, "lon": -0.1389407}, {"type": "node", "id": 1782296079, "lat": 51.4896514, "lon": -0.1390612}, {"type": "node", "id": 1782296089, "lat": 51.4898664, "lon": -0.139012}, {"type": "node", "id": 1782296091, "lat": 51.4896456, "lon": -0.1389204}, {"type": "node", "id": 1782296094, "lat": 51.4896568, "lon": -0.1390802}, {"type": "node", "id": 1782296095, "lat": 51.4898655, "lon": -0.1390802}, {"type": "node", "id": 1782296103, "lat": 51.4896576, "lon": -0.1389581}, {"type": "node", "id": 1782296105, "lat": 51.4896484, "lon": -0.138993}, {"type": "node", "id": 1782296109, "lat": 51.4896264, "lon": -0.1391993}, {"type": "node", "id": 1782296111, "lat": 51.4898672, "lon": -0.1390238}, {"type": "node", "id": 1782296115, "lat": 51.4895854, "lon": -0.1392395}, {"type": "node", "id": 1782296117, "lat": 51.4897573, "lon": -0.1391144}, {"type": "node", "id": 1782296123, "lat": 51.4895482, "lon": -0.1388454}, {"type": "node", "id": 1784648707, "lat": 51.4935566, "lon": -0.1435057}, {"type": "node", "id": 1784648712, "lat": 51.4934944, "lon": -0.1434523}, {"type": "node", "id": 1784648714, "lat": 51.4934539, "lon": -0.1437463}, {"type": "node", "id": 1784648736, "lat": 51.4932642, "lon": -0.1433875}, {"type": "node", "id": 1784648739, "lat": 51.4935712, "lon": -0.1434994}, {"type": "node", "id": 1784648742, "lat": 51.4933761, "lon": -0.1434519}, {"type": "node", "id": 1784648744, "lat": 51.4934017, "lon": -0.1437764}, {"type": "node", "id": 1784648745, "lat": 51.4933124, "lon": -0.1433665}, {"type": "node", "id": 1784648751, "lat": 51.4934418, "lon": -0.1436883}, {"type": "node", "id": 1784648753, "lat": 51.4932698, "lon": -0.1435247}, {"type": "node", "id": 1784648760, "lat": 51.4936063, "lon": -0.1435717}, {"type": "node", "id": 1784648767, "lat": 51.4933516, "lon": -0.1434804}, {"type": "node", "id": 1784648770, "lat": 51.4934877, "lon": -0.1434147}, {"type": "node", "id": 1784648774, "lat": 51.4934978, "lon": -0.1435156}, {"type": "node", "id": 1784648776, "lat": 51.4935061, "lon": -0.1433893}, {"type": "node", "id": 1784648783, "lat": 51.493367, "lon": -0.1435155}, {"type": "node", "id": 1784648787, "lat": 51.4933335, "lon": -0.1436332}, {"type": "node", "id": 1784648790, "lat": 51.4935604, "lon": -0.1434896}, {"type": "node", "id": 1784648791, "lat": 51.4933307, "lon": -0.1433534}, {"type": "node", "id": 1784648792, "lat": 51.4934778, "lon": -0.1436461}, {"type": "node", "id": 1784648793, "lat": 51.4935213, "lon": -0.1434334}, {"type": "node", "id": 1784648797, "lat": 51.4934919, "lon": -0.1434778}, {"type": "node", "id": 1784648798, "lat": 51.4935267, "lon": -0.1435296}, {"type": "node", "id": 1784648810, "lat": 51.4933682, "lon": -0.1431585}, {"type": "node", "id": 1784648820, "lat": 51.493547, "lon": -0.1434394}, {"type": "node", "id": 1784648822, "lat": 51.4934002, "lon": -0.1434764}, {"type": "node", "id": 1784648826, "lat": 51.4935167, "lon": -0.1435249}, {"type": "node", "id": 1784648828, "lat": 51.4935081, "lon": -0.1435148}, {"type": "node", "id": 1784648830, "lat": 51.4935666, "lon": -0.1435182}, {"type": "node", "id": 1784648832, "lat": 51.4934927, "lon": -0.1434967}, {"type": "node", "id": 1784648835, "lat": 51.4935118, "lon": -0.1434412}, {"type": "node", "id": 1784648838, "lat": 51.4936163, "lon": -0.1435234}, {"type": "node", "id": 1784648849, "lat": 51.4932813, "lon": -0.1435902}, {"type": "node", "id": 1784648857, "lat": 51.4933925, "lon": -0.1431881}, {"type": "node", "id": 1784648861, "lat": 51.493547, "lon": -0.1435421}, {"type": "node", "id": 1784648867, "lat": 51.4935704, "lon": -0.143628}, {"type": "node", "id": 1784648869, "lat": 51.4935008, "lon": -0.1434661}, {"type": "node", "id": 1784648871, "lat": 51.4935584, "lon": -0.1435333}, {"type": "node", "id": 1784648875, "lat": 51.4936252, "lon": -0.1435403}, {"type": "node", "id": 1784648878, "lat": 51.4934926, "lon": -0.1433844}, {"type": "node", "id": 1784648882, "lat": 51.4934092, "lon": -0.1431935}, {"type": "node", "id": 1784648883, "lat": 51.4934343, "lon": -0.1432002}, {"type": "node", "id": 1784648887, "lat": 51.4935312, "lon": -0.143545}, {"type": "node", "id": 1784648892, "lat": 51.493573, "lon": -0.1434787}, {"type": "node", "id": 1784648896, "lat": 51.493421, "lon": -0.1437825}, {"type": "node", "id": 1784648902, "lat": 51.4935, "lon": -0.1434894}, {"type": "node", "id": 1784648904, "lat": 51.4936004, "lon": -0.1434013}, {"type": "node", "id": 1784648906, "lat": 51.4935057, "lon": -0.1434509}, {"type": "node", "id": 1784648910, "lat": 51.4936305, "lon": -0.1434416}, {"type": "node", "id": 1784648912, "lat": 51.4935854, "lon": -0.1433772}, {"type": "node", "id": 1784648919, "lat": 51.4935288, "lon": -0.1434326}, {"type": "node", "id": 1784648921, "lat": 51.4935687, "lon": -0.143455}, {"type": "node", "id": 1784648927, "lat": 51.4934524, "lon": -0.1437129}, {"type": "node", "id": 1784648938, "lat": 51.4934459, "lon": -0.1432055}, {"type": "node", "id": 1784648940, "lat": 51.4934375, "lon": -0.1437644}, {"type": "node", "id": 1784648942, "lat": 51.4935536, "lon": -0.1434488}, {"type": "node", "id": 1784648944, "lat": 51.4935052, "lon": -0.1435287}, {"type": "node", "id": 1784648946, "lat": 51.4935587, "lon": -0.1434322}, {"type": "node", "id": 1784648950, "lat": 51.4936238, "lon": -0.143397}, {"type": "node", "id": 1784648959, "lat": 51.4932815, "lon": -0.1433598}, {"type": "node", "id": 1784648961, "lat": 51.4934349, "lon": -0.1432878}, {"type": "node", "id": 1784648968, "lat": 51.4936138, "lon": -0.143577}, {"type": "node", "id": 1784648969, "lat": 51.4935183, "lon": -0.1435423}, {"type": "node", "id": 1784648973, "lat": 51.4936338, "lon": -0.1434818}, {"type": "node", "id": 1784648974, "lat": 51.4935037, "lon": -0.1435055}, {"type": "node", "id": 1784648975, "lat": 51.4936163, "lon": -0.1434858}, {"type": "node", "id": 1784648976, "lat": 51.4933792, "lon": -0.1431787}, {"type": "node", "id": 1784648977, "lat": 51.4934626, "lon": -0.1437366}, {"type": "node", "id": 1784648978, "lat": 51.4935609, "lon": -0.1434804}, {"type": "node", "id": 1784648982, "lat": 51.4936113, "lon": -0.1435556}, {"type": "node", "id": 1784648985, "lat": 51.4936214, "lon": -0.1434056}, {"type": "node", "id": 1784648998, "lat": 51.4934081, "lon": -0.1437955}, {"type": "node", "id": 1784649009, "lat": 51.4934807, "lon": -0.1433979}, {"type": "node", "id": 1784649015, "lat": 51.493559, "lon": -0.1434636}, {"type": "node", "id": 1784649021, "lat": 51.4935373, "lon": -0.1435286}, {"type": "node", "id": 1784649039, "lat": 51.4935497, "lon": -0.1435187}, {"type": "node", "id": 1784649044, "lat": 51.4932539, "lon": -0.1434952}, {"type": "node", "id": 1784649046, "lat": 51.4936121, "lon": -0.1434442}, {"type": "node", "id": 1784649048, "lat": 51.493567, "lon": -0.1436159}, {"type": "node", "id": 1784649059, "lat": 51.4934936, "lon": -0.1434345}, {"type": "node", "id": 1784649063, "lat": 51.4933968, "lon": -0.1431084}, {"type": "node", "id": 1784649070, "lat": 51.4936297, "lon": -0.1435155}, {"type": "node", "id": 1784649075, "lat": 51.493456, "lon": -0.1432136}, {"type": "node", "id": 1784649088, "lat": 51.4932381, "lon": -0.143441}, {"type": "node", "id": 1960864468, "lat": 51.4919452, "lon": -0.1384082, "tags": {"ref:GB:tflcid": "RWG055496", "traffic_calming": "table"}}, {"type": "node", "id": 1962707672, "lat": 51.4921811, "lon": -0.1473261}, {"type": "node", "id": 2151161514, "lat": 51.4925673, "lon": -0.1421318}, {"type": "node", "id": 2151161573, "lat": 51.4925627, "lon": -0.1421221}, {"type": "node", "id": 2218438027, "lat": 51.4922075, "lon": -0.1498272, "tags": {"access": "yes", "amenity": "parking", "capacity": "244", "fee": "yes", "name": "NCP Victoria Car Park", "operator": "NCP", "parking": "multi-storey", "website": "https://www.ncp.co.uk/find-a-car-park/car-parks/london-victoria/"}}, {"type": "node", "id": 2497925215, "lat": 51.489557, "lon": -0.138807}, {"type": "node", "id": 2497968615, "lat": 51.4924336, "lon": -0.1416527}, {"type": "node", "id": 2601602111, "lat": 51.4920829, "lon": -0.1386306}, {"type": "node", "id": 2673046711, "lat": 51.4922015, "lon": -0.1387457}, {"type": "node", "id": 2882710732, "lat": 51.4920432, "lon": -0.1385924, "tags": {"entrance": "main"}}, {"type": "node", "id": 2882710735, "lat": 51.4922223, "lon": -0.1387658}, {"type": "node", "id": 3224182243, "lat": 51.4923457, "lon": -0.1388855}, {"type": "node", "id": 3287373042, "lat": 51.4921348, "lon": -0.1384029}, {"type": "node", "id": 3287373043, "lat": 51.4920857, "lon": -0.138511}, {"type": "node", "id": 3287373810, "lat": 51.4920377, "lon": -0.1384696}, {"type": "node", "id": 3391845772, "lat": 51.4905131, "lon": -0.1378304}, {"type": "node", "id": 3391845773, "lat": 51.4904728, "lon": -0.1377342}, {"type": "node", "id": 3391845774, "lat": 51.4904254, "lon": -0.1377853}, {"type": "node", "id": 3391845775, "lat": 51.4904658, "lon": -0.1378815}, {"type": "node", "id": 4437495160, "lat": 51.4920174, "lon": -0.1384561}, {"type": "node", "id": 4437495161, "lat": 51.4920195, "lon": -0.1385419}, {"type": "node", "id": 4437495166, "lat": 51.4920343, "lon": -0.1385011}, {"type": "node", "id": 4437495172, "lat": 51.4920736, "lon": -0.1386203, "tags": {"entrance": "yes", "note": "Entrance to 16A"}}, {"type": "node", "id": 4437495174, "lat": 51.4921178, "lon": -0.1386645, "tags": {"entrance": "yes", "note": "Entrance to 44A"}}, {"type": "node", "id": 4437495175, "lat": 51.492123, "lon": -0.1386695}, {"type": "node", "id": 4437495177, "lat": 51.4921604, "lon": -0.1387058}, {"type": "node", "id": 4437495197, "lat": 51.4921824, "lon": -0.1384449}, {"type": "node", "id": 4444738580, "lat": 51.492279, "lon": -0.1388208}, {"type": "node", "id": 4444739012, "lat": 51.4923093, "lon": -0.138566}, {"type": "node", "id": 4444739013, "lat": 51.4923124, "lon": -0.1388532}, {"type": "node", "id": 4444739016, "lat": 51.4923223, "lon": -0.1386043}, {"type": "node", "id": 4444739025, "lat": 51.4923745, "lon": -0.1386552}, {"type": "node", "id": 5205080377, "lat": 51.489862, "lon": -0.1387626}, {"type": "node", "id": 5205080378, "lat": 51.4897546, "lon": -0.1388833}, {"type": "node", "id": 5205080379, "lat": 51.4898573, "lon": -0.138974}, {"type": "node", "id": 5205080380, "lat": 51.4897454, "lon": -0.1388833}, {"type": "node", "id": 5205080381, "lat": 51.4896513, "lon": -0.1390283}, {"type": "node", "id": 5267783266, "lat": 51.4940274, "lon": -0.1485075}, {"type": "node", "id": 5267783267, "lat": 51.4938098, "lon": -0.1486821}, {"type": "node", "id": 5267783318, "lat": 51.4936914, "lon": -0.1488529}, {"type": "node", "id": 5267783319, "lat": 51.4936246, "lon": -0.1487039}, {"type": "node", "id": 5267784221, "lat": 51.4937535, "lon": -0.1489899}, {"type": "node", "id": 5267784226, "lat": 51.4937237, "lon": -0.1491331}, {"type": "node", "id": 5267784231, "lat": 51.4939049, "lon": -0.1489435}, {"type": "node", "id": 7542376261, "lat": 51.4880538, "lon": -0.1505413, "tags": {"amenity": "parking", "layer": "-1", "parking": "underground"}}, {"type": "node", "id": 7878874337, "lat": 51.4914415, "lon": -0.1516889}, {"type": "node", "id": 7878874338, "lat": 51.4914685, "lon": -0.1514483}, {"type": "node", "id": 7878874339, "lat": 51.4914273, "lon": -0.1513401}, {"type": "node", "id": 7878874340, "lat": 51.491306, "lon": -0.151304}, {"type": "node", "id": 7878874341, "lat": 51.4912663, "lon": -0.1513545}, {"type": "node", "id": 7878874342, "lat": 51.4912595, "lon": -0.1514676}, {"type": "node", "id": 7878874343, "lat": 51.4913412, "lon": -0.1516708}, {"type": "node", "id": 8116370689, "lat": 51.4937292, "lon": -0.149144}, {"type": "node", "id": 8116370691, "lat": 51.4937422, "lon": -0.1485377}, {"type": "node", "id": 8116370693, "lat": 51.4938655, "lon": -0.1488641}, {"type": "node", "id": 8116370694, "lat": 51.493761, "lon": -0.1485206}, {"type": "node", "id": 8116370696, "lat": 51.4938143, "lon": -0.1490512}, {"type": "node", "id": 8116370699, "lat": 51.4941059, "lon": -0.1485842}, {"type": "node", "id": 8116370700, "lat": 51.4940623, "lon": -0.1484795}, {"type": "node", "id": 8427219240, "lat": 51.4870519, "lon": -0.1426359}, {"type": "node", "id": 8427219241, "lat": 51.4870118, "lon": -0.1426734}, {"type": "node", "id": 8427219242, "lat": 51.4869859, "lon": -0.1428129}, {"type": "node", "id": 8427219243, "lat": 51.4869366, "lon": -0.1428638}, {"type": "node", "id": 9084194288, "lat": 51.4862453, "lon": -0.1387486}, {"type": "node", "id": 9084194289, "lat": 51.4862272, "lon": -0.1387412}, {"type": "node", "id": 9084194290, "lat": 51.4861576, "lon": -0.1391763}, {"type": "node", "id": 9084194291, "lat": 51.4861757, "lon": -0.1391838}, {"type": "node", "id": 9084194292, "lat": 51.4860764, "lon": -0.1400685}, {"type": "node", "id": 9084194293, "lat": 51.4861185, "lon": -0.1397896}, {"type": "node", "id": 9084194294, "lat": 51.4861364, "lon": -0.1395544}, {"type": "node", "id": 9084194295, "lat": 51.4861185, "lon": -0.1395503}, {"type": "node", "id": 9084194296, "lat": 51.4861028, "lon": -0.1397869}, {"type": "node", "id": 9084194297, "lat": 51.4860606, "lon": -0.1400624}, {"type": "node", "id": 9084194298, "lat": 51.4859293, "lon": -0.1409514}, {"type": "node", "id": 9084194299, "lat": 51.4859438, "lon": -0.1409555}, {"type": "node", "id": 9084194300, "lat": 51.4859625, "lon": -0.1407997}, {"type": "node", "id": 9084194301, "lat": 51.4859931, "lon": -0.1406007}, {"type": "node", "id": 9084194302, "lat": 51.4860323, "lon": -0.1403505}, {"type": "node", "id": 9084194303, "lat": 51.4860153, "lon": -0.140343}, {"type": "node", "id": 9084194304, "lat": 51.4859753, "lon": -0.140598}, {"type": "node", "id": 9084194305, "lat": 51.4859463, "lon": -0.1407962}, {"type": "node", "id": 9084194306, "lat": 51.4858985, "lon": -0.1407759}, {"type": "node", "id": 9084194307, "lat": 51.4859153, "lon": -0.1407805}, {"type": "node", "id": 9084194308, "lat": 51.4859009, "lon": -0.140899}, {"type": "node", "id": 9084194309, "lat": 51.4858946, "lon": -0.1410499}, {"type": "node", "id": 9084194310, "lat": 51.4858975, "lon": -0.141252}, {"type": "node", "id": 9084194311, "lat": 51.4859033, "lon": -0.1414037}, {"type": "node", "id": 9084194312, "lat": 51.4858854, "lon": -0.141406}, {"type": "node", "id": 9084194313, "lat": 51.4858792, "lon": -0.141252}, {"type": "node", "id": 9084194314, "lat": 51.4858768, "lon": -0.1410491}, {"type": "node", "id": 9084194315, "lat": 51.485883, "lon": -0.1408966}, {"type": "node", "id": 9084194316, "lat": 51.4859307, "lon": -0.141398}, {"type": "node", "id": 9084217217, "lat": 51.4859489, "lon": -0.1413969}, {"type": "node", "id": 9084217218, "lat": 51.4859615, "lon": -0.1415924}, {"type": "node", "id": 9084217219, "lat": 51.485986, "lon": -0.1417734}, {"type": "node", "id": 9084217220, "lat": 51.485972, "lon": -0.1417812}, {"type": "node", "id": 9084217221, "lat": 51.4859461, "lon": -0.1415969}, {"type": "node", "id": 9084217222, "lat": 51.4859137, "lon": -0.1417234}, {"type": "node", "id": 9084217223, "lat": 51.4859313, "lon": -0.1417168}, {"type": "node", "id": 9084217224, "lat": 51.485967, "lon": -0.141916}, {"type": "node", "id": 9084217225, "lat": 51.4860182, "lon": -0.1421243}, {"type": "node", "id": 9084217226, "lat": 51.486002, "lon": -0.1421334}, {"type": "node", "id": 9084217227, "lat": 51.4859505, "lon": -0.1419233}, {"type": "node", "id": 9084217228, "lat": 51.4861062, "lon": -0.1422982}, {"type": "node", "id": 9084217229, "lat": 51.4861231, "lon": -0.1422888}, {"type": "node", "id": 9084217230, "lat": 51.4861949, "lon": -0.1426219}, {"type": "node", "id": 9084217231, "lat": 51.486178, "lon": -0.1426313}, {"type": "node", "id": 9084217232, "lat": 51.4860327, "lon": -0.1397026}, {"type": "node", "id": 9084217233, "lat": 51.4860463, "lon": -0.1396155}, {"type": "node", "id": 9084217234, "lat": 51.4855422, "lon": -0.1394124}, {"type": "node", "id": 9084217235, "lat": 51.4855286, "lon": -0.1394997}, {"type": "node", "id": 9084217236, "lat": 51.4860968, "lon": -0.1424617}, {"type": "node", "id": 9084217237, "lat": 51.4861126, "lon": -0.1424541}, {"type": "node", "id": 9084217238, "lat": 51.4862245, "lon": -0.1430517}, {"type": "node", "id": 9084217239, "lat": 51.4862089, "lon": -0.1430593}, {"type": "node", "id": 9084217240, "lat": 51.4862398, "lon": -0.1429738}, {"type": "node", "id": 9084217241, "lat": 51.4862546, "lon": -0.142967}, {"type": "node", "id": 9084217242, "lat": 51.4863588, "lon": -0.1435572}, {"type": "node", "id": 9084217243, "lat": 51.4863441, "lon": -0.1435639}, {"type": "node", "id": 9084217244, "lat": 51.4862583, "lon": -0.1433325}, {"type": "node", "id": 9084217245, "lat": 51.4862737, "lon": -0.1433276}, {"type": "node", "id": 9084217246, "lat": 51.486325, "lon": -0.1436541}, {"type": "node", "id": 9084217247, "lat": 51.4863454, "lon": -0.1438804}, {"type": "node", "id": 9084217248, "lat": 51.4863256, "lon": -0.1438814}, {"type": "node", "id": 9084217249, "lat": 51.4863071, "lon": -0.1436551}, {"type": "node", "id": 9084217250, "lat": 51.486392, "lon": -0.1438636}, {"type": "node", "id": 9084217251, "lat": 51.4864428, "lon": -0.1446726}, {"type": "node", "id": 9084217252, "lat": 51.4864246, "lon": -0.1446755}, {"type": "node", "id": 9084217253, "lat": 51.4863739, "lon": -0.1438665}, {"type": "node", "id": 9084217254, "lat": 51.4863658, "lon": -0.1441978}, {"type": "node", "id": 9084217255, "lat": 51.4863947, "lon": -0.1446625}, {"type": "node", "id": 9084217256, "lat": 51.4863763, "lon": -0.1446654}, {"type": "node", "id": 9084217257, "lat": 51.4863474, "lon": -0.1442007}, {"type": "node", "id": 9084217258, "lat": 51.4862931, "lon": -0.1439151}, {"type": "node", "id": 9084217259, "lat": 51.4863026, "lon": -0.1440012}, {"type": "node", "id": 9084217260, "lat": 51.4859712, "lon": -0.1440953}, {"type": "node", "id": 9084217261, "lat": 51.4859618, "lon": -0.1440091}, {"type": "node", "id": 9084217262, "lat": 51.4863324, "lon": -0.1448386}, {"type": "node", "id": 9084217263, "lat": 51.4863369, "lon": -0.1448757}, {"type": "node", "id": 9084217264, "lat": 51.4861092, "lon": -0.1449469}, {"type": "node", "id": 9084217265, "lat": 51.4861047, "lon": -0.1449097}, {"type": "node", "id": 9084217266, "lat": 51.4859208, "lon": -0.1440957}, {"type": "node", "id": 9084217267, "lat": 51.4860162, "lon": -0.1449056}, {"type": "node", "id": 9084217268, "lat": 51.4859723, "lon": -0.1449189}, {"type": "node", "id": 9084217269, "lat": 51.4858771, "lon": -0.144109}, {"type": "node", "id": 9170427427, "lat": 51.4866862, "lon": -0.1459525}, {"type": "node", "id": 9170427428, "lat": 51.4864887, "lon": -0.1458665}, {"type": "node", "id": 9336966021, "lat": 51.4865291, "lon": -0.1458841}, {"type": "node", "id": 10175917715, "lat": 51.4866741, "lon": -0.1502228, "tags": {"access": "private", "amenity": "parking"}}, {"type": "node", "id": 11014992100, "lat": 51.4937285, "lon": -0.1485474}, {"type": "node", "id": 11014992103, "lat": 51.4937334, "lon": -0.1491523}, {"type": "node", "id": 11016967979, "lat": 51.4940405, "lon": -0.148497}, {"type": "node", "id": 11016967980, "lat": 51.4939756, "lon": -0.1487328}, {"type": "node", "id": 11016967982, "lat": 51.4938935, "lon": -0.1489206}, {"type": "node", "id": 11016967994, "lat": 51.4938963, "lon": -0.1486972}, {"type": "node", "id": 11016967995, "lat": 51.4938779, "lon": -0.1486311}, {"type": "node", "id": 11016967996, "lat": 51.4938297, "lon": -0.1487489}, {"type": "node", "id": 11016967999, "lat": 51.4937831, "lon": -0.1490597}, {"type": "node", "id": 11016968003, "lat": 51.4936112, "lon": -0.1487197}, {"type": "node", "id": 11016968004, "lat": 51.4935885, "lon": -0.1486586}, {"type": "node", "id": 11016978707, "lat": 51.493803, "lon": -0.1490666}, {"type": "node", "id": 11167464116, "lat": 51.4938718, "lon": -0.1487166}, {"type": "way", "id": 4249941, "nodes": [18130217, 1231977787, 3287373043, 3287373810, 4437495160, 1960864468], "tags": {"bicycle": "yes", "highway": "pedestrian", "motor_vehicle": "no", "motor_vehicle:conditional": "delivery @ (Mo-Sa 16:00-10:00)", "name": "Tachbrook Street", "note": "Pedestrian zone. No motor vehicles except for loading Mon-Sat Midnight-10am, 4pm-Midnight, Sunday At any time"}}, {"type": "way", "id": 48865384, "nodes": [620025016, 1231977787, 620025015, 4444739025, 4444739016, 1231977830, 4444739012, 271387568, 4437495197, 3287373042, 620025020, 3287373810, 4437495166, 620025021, 4437495161, 620025023, 2882710732, 4437495172, 2601602111, 4437495174, 4437495175, 4437495177, 2673046711, 2882710735, 805907475, 4444738580, 4444739013, 3224182243, 620025016], "tags": {"addr:city": "London", "addr:postcode": "SW1V 2JS", "addr:street": "Tachbrook Street", "amenity": "marketplace", "area": "yes", "building": "no", "highway": "pedestrian", "maxspeed": "20 mph", "maxspeed:type": "GB:zone20", "name": "Tachbrook Street Market", "opening_hours": "Mo-Sa 08:00-18:00", "operator": "City of Westminster", "website": "https://www.westminster.gov.uk/markets-available-guide"}}, {"type": "way", "id": 57010894, "nodes": [711535602, 1537073358, 1537073382, 96087864, 711535603, 711535596, 711535597, 711535598, 711535600, 711535602], "tags": {"addr:city": "London", "addr:country": "GB", "addr:postcode": "SW1W 9SJ", "amenity": "parking", "fee": "yes", "name": "Apcoa Ecclestone Bridge", "operator": "Apcoa"}}, {"type": "way", "id": 74661956, "nodes": [128366303, 1233349762, 128366302, 8427219240, 128345838, 8427219241, 8427219242, 881874783, 8427219243, 881874786], "tags": {"foot": "yes", "highway": "pedestrian", "name": "Glasgow Terrace", "source": "OS"}}, {"type": "way", "id": 98866322, "nodes": [866630971, 1143756039, 1143756040, 1143756041, 1143756042, 1143756044, 1143756045, 1143756047, 1143756048, 866630971], "tags": {"amenity": "parking", "source": "Bing"}}, {"type": "way", "id": 111757759, "nodes": [1272466386, 1272466410, 1272466369, 1272466370, 1272466382, 1272466384, 1272466411, 1272466385, 1272466386], "tags": {"amenity": "parking", "source": "Bing"}}, {"type": "way", "id": 111760006, "nodes": [1272481505, 1962707672, 1272481492, 1272481493, 1272481494, 1272481500, 1272481514, 1272481517, 1272481519, 1272481505], "tags": {"amenity": "parking", "source": "Bing"}}, {"type": "way", "id": 111760007, "nodes": [1232048602, 1272481526, 1272481312, 1272481314, 1272481316, 1272481386, 1272481384, 1232048602], "tags": {"amenity": "parking", "source": "Bing"}}, {"type": "way", "id": 166792080, "nodes": [1782296115, 1782296109, 1782295998, 1782296014, 1782296007, 1782296001, 1782296094, 1782296079, 5205080381, 1782295990, 1782296105, 1782296071, 1782296103, 1782296075, 1782296091, 1782295993, 1782296004, 1782295984, 1782296123, 2497925215, 5205080380, 5205080378, 5205080377, 1782296002, 1782296073, 1782296006, 1782296039, 1782296051, 1782295988, 1782296035, 5205080379, 1782296089, 1782296111, 1782296013, 1782296026, 1782296095, 1782295986, 1782295982, 1782296022, 1782296016, 1782295992, 1782296054, 1782296117, 1782296003, 1782296047, 1782296115], "tags": {"area": "yes", "highway": "pedestrian", "source": "Bing"}}, {"type": "way", "id": 167057954, "nodes": [1784648998, 1784648896, 1784648940, 1784648714, 1784648977, 1784648927, 1784648751, 1784648792, 1784648822, 1784648783, 1784648767, 1784648742, 1784648791, 1784648745, 1784648959, 1784648736, 1784649088, 1784649044, 1784648753, 1784648849, 1784648787, 1784648744, 1784648998], "tags": {"amenity": "parking", "source": "Bing"}}, {"type": "way", "id": 167057956, "nodes": [1784648946, 1784648961, 1784648776, 1784648820, 1784648942, 1784649015, 1784648978, 1784648790, 1784648707, 1784649039, 1784649021, 1784648798, 1784648826, 1784648828, 1784648974, 1784648902, 1784648869, 1784648906, 1784648835, 1784648793, 1784648919, 1784648878, 1784649009, 1784648770, 1784649059, 1784648712, 1784648797, 1784648832, 1784648774, 1784648944, 1784648969, 1784648887, 1784648861, 1784648871, 1784648830, 1784648739, 1784648892, 1784648921, 1784648946], "tags": {"area": "yes", "highway": "pedestrian", "source": "Bing"}}, {"type": "way", "id": 167057959, "nodes": [1784648867, 1784648968, 1784648875, 1784649070, 1784648973, 1784648910, 1784648985, 1784648950, 1784649063, 1784648810, 1784648976, 1784648857, 1784648882, 1784648883, 1784648938, 1784649075, 1784648912, 1784648904, 1784649046, 1784648975, 1784648838, 1784648982, 1784648760, 1784649048, 1784648867], "tags": {"area": "yes", "highway": "pedestrian", "source": "Bing"}}, {"type": "way", "id": 242293791, "nodes": [1283446759, 2151161573, 2151161514, 1283446760, 1283446753, 2497968615, 1283446759], "tags": {"access": "private", "amenity": "parking", "parking": "surface"}}, {"type": "way", "id": 332072723, "nodes": [3391845772, 3391845773, 3391845774, 3391845775, 3391845772], "tags": {"access": "private", "amenity": "parking", "capacity": "6"}}, {"type": "way", "id": 844594342, "nodes": [7878874337, 7878874338, 7878874339, 7878874340, 7878874341, 7878874342, 7878874343, 7878874337], "tags": {"access": "private", "amenity": "parking", "capacity": "27", "parking": "surface"}}, {"type": "way", "id": 871359442, "nodes": [8116370691, 11014992100, 11016968004, 11016968003, 5267783319, 5267783318, 5267784221, 11016967999, 5267784226, 8116370689, 11014992103, 11016978707, 8116370696, 5267784231, 11016967982, 8116370693, 11016967996, 5267783267, 8116370694, 8116370691], "tags": {"area": "yes"}}, {"type": "way", "id": 871359445, "nodes": [11016967994, 11167464116, 11016967996, 8116370693, 11016967980, 8116370699, 8116370700, 11016967979, 5267783266, 11016967995, 11016967994], "tags": {"area": "yes"}}, {"type": "way", "id": 982248600, "nodes": [9084194288, 9084194289, 9084194290, 9084194291, 9084194288], "tags": {"amenity": "parking", "capacity": "6", "parking": "lane"}}, {"type": "way", "id": 982248601, "nodes": [9084194292, 9084194293, 9084194294, 9084194295, 9084194296, 9084194297, 9084194292], "tags": {"amenity": "parking", "capacity": "6", "parking": "lane"}}, {"type": "way", "id": 982248602, "nodes": [9084194298, 9084194299, 9084194300, 9084194301, 9084194302, 9084194303, 9084194304, 9084194305, 9084194298], "tags": {"amenity": "parking", "capacity": "8", "parking": "lane"}}, {"type": "way", "id": 982248603, "nodes": [9084194306, 9084194307, 9084194308, 9084194309, 9084194310, 9084194311, 9084194312, 9084194313, 9084194314, 9084194315, 9084194306], "tags": {"amenity": "parking", "capacity": "8", "parking": "lane"}}, {"type": "way", "id": 982248604, "nodes": [9084194316, 9084217217, 9084217218, 9084217219, 9084217220, 9084217221, 9084194316], "tags": {"amenity": "parking", "capacity": "6", "parking": "lane"}}, {"type": "way", "id": 982248605, "nodes": [9084217222, 9084217223, 9084217224, 9084217225, 9084217226, 9084217227, 9084217222], "tags": {"amenity": "parking", "capacity": "6", "parking": "lane"}}, {"type": "way", "id": 982248606, "nodes": [9084217228, 9084217229, 9084217230, 9084217231, 9084217228], "tags": {"amenity": "parking", "capacity": "4", "capacity:disabled": "1", "parking": "lane"}}, {"type": "way", "id": 982248607, "nodes": [9084217232, 9084217233, 9084217234, 9084217235, 9084217232], "tags": {"amenity": "parking", "capacity": "21", "parking": "street_side"}}, {"type": "way", "id": 982248608, "nodes": [9084217236, 9084217237, 9084217238, 9084217239, 9084217236], "tags": {"amenity": "parking", "capacity": "8", "parking": "lane"}}, {"type": "way", "id": 982248609, "nodes": [9084217240, 9084217241, 9084217242, 9084217243, 9084217240], "tags": {"amenity": "parking", "capacity": "9", "parking": "lane"}}, {"type": "way", "id": 982248610, "nodes": [9084217244, 9084217245, 9084217246, 9084217247, 9084217248, 9084217249, 9084217244], "tags": {"amenity": "parking", "capacity": "8", "parking": "lane"}}, {"type": "way", "id": 982248611, "nodes": [9084217250, 9084217251, 9084217252, 9084217253, 9084217250], "tags": {"amenity": "parking", "capacity": "10", "capacity:disabled": "1", "parking": "lane"}}, {"type": "way", "id": 982248612, "nodes": [9084217254, 9084217255, 9084217256, 9084217257, 9084217254], "tags": {"amenity": "parking", "capacity": "6", "parking": "lane"}}, {"type": "way", "id": 982248613, "nodes": [9084217258, 9084217259, 9084217260, 9084217261, 9084217258], "tags": {"amenity": "parking", "capacity": "16", "parking": "street_side"}}, {"type": "way", "id": 982248614, "nodes": [9084217262, 9084217263, 9084217264, 9084217265, 9084217262], "tags": {"amenity": "parking", "capacity": "5", "parking": "lane"}}, {"type": "way", "id": 982248615, "nodes": [9084217266, 9084217267, 9084217268, 9084217269, 9084217266], "tags": {"amenity": "parking", "parking": "street_side"}}, {"type": "way", "id": 992552406, "nodes": [447110754, 9170427427], "tags": {"highway": "pedestrian", "layer": "-1"}}, {"type": "way", "id": 1012038318, "nodes": [9336966021, 9170427428, 447110769], "tags": {"highway": "pedestrian", "layer": "-1"}}, {"type": "way", "id": 1012038319, "nodes": [9170427427, 9336966021], "tags": {"highway": "pedestrian", "layer": "-1", "tunnel": "yes"}}, {"type": "relation", "id": 16034249, "members": [{"type": "way", "ref": 871359442, "role": "outer"}, {"type": "way", "ref": 871359445, "role": "outer"}], "tags": {"area": "yes", "highway": "pedestrian", "name": "Eccleston Yards", "surface": "concrete:plates", "type": "multipolygon"}}]}